pydblite/__init__.py
pydblite/common.py
pydblite/pydblite.py
pydblite/pydblite_conversions.py
pydblite/sqlite.py
PyDbLite3-3.1.1.dist-info/LICENCE.txt
PyDbLite3-3.1.1.dist-info/METADATA
PyDbLite3-3.1.1.dist-info/WHEEL
PyDbLite3-3.1.1.dist-info/top_level.txt
PyDbLite3-3.1.1.dist-info/RECORD
